hosting_benchmark/__init__.py
hosting_benchmark/benchmark.py
hosting_benchmark/version.py
hosting_benchmark/commands/__init__.py
hosting_benchmark/commands/all.py
hosting_benchmark/commands/archive.py
hosting_benchmark/commands/cpu.py
hosting_benchmark/commands/info.py
hosting_benchmark/commands/io.py
hosting_benchmark/commands/mysql.py
hosting_benchmark/inc/__init__.py
hosting_benchmark/inc/formatters.py
hosting_benchmark/inc/taxonomies.py
hosting_benchmark/inc/tools.py
hosting_benchmark/server/LoremIpsum.php
hosting_benchmark/server/config.example.php
hosting_benchmark/server/fake_data.php
hosting_benchmark/server/inc.php
hosting_benchmark/server/index.php
hosting_benchmark/server/api/cpu.php
hosting_benchmark/server/api/info.php
hosting_benchmark/server/api/io.php
hosting_benchmark/server/api/mysql.php
tests/__init__.py
hosting_benchmark-0.0.6.dist-info/LICENSE
hosting_benchmark-0.0.6.dist-info/METADATA
hosting_benchmark-0.0.6.dist-info/WHEEL
hosting_benchmark-0.0.6.dist-info/entry_points.txt
hosting_benchmark-0.0.6.dist-info/top_level.txt
hosting_benchmark-0.0.6.dist-info/RECORD
