Metadata-Version: 2.1
Name: hosting-benchmark
Version: 0.0.6
Summary: PHP Web-hosting benchmark
Home-page: https://github.com/samupl/hosting-benchmark
Author: Jakub Szafrański
Author-email: kontakt@samu.pl
License: UNKNOWN
Platform: UNKNOWN
Requires-Dist: click
Requires-Dist: requests
Requires-Dist: terminaltables
Provides-Extra: dev
Requires-Dist: ipython ; extra == 'dev'
Requires-Dist: twine ; extra == 'dev'
Requires-Dist: pre-commit ; extra == 'dev'
Provides-Extra: test
Requires-Dist: mock ; extra == 'test'
Requires-Dist: munch ; extra == 'test'
Requires-Dist: pytest ; extra == 'test'
Requires-Dist: pytest-mock (<3.0) ; extra == 'test'
